ydata_synthetic/__init__.py
ydata_synthetic/version.py
ydata_synthetic/streamlit_app/__init__.py
ydata_synthetic/streamlit_app/run.py
ydata_synthetic/synthesizers/__init__.py
ydata_synthetic/synthesizers/base.py
ydata_synthetic/synthesizers/regular/__init__.py
ydata_synthetic/synthesizers/regular/cgan/__init__.py
ydata_synthetic/synthesizers/regular/cgan/model.py
ydata_synthetic/synthesizers/regular/cramergan/__init__.py
ydata_synthetic/synthesizers/regular/cramergan/model.py
ydata_synthetic/synthesizers/regular/ctgan/__init__.py
ydata_synthetic/synthesizers/regular/ctgan/model.py
ydata_synthetic/synthesizers/regular/cwgangp/__init__.py
ydata_synthetic/synthesizers/regular/cwgangp/model.py
ydata_synthetic/synthesizers/regular/dragan/__init__.py
ydata_synthetic/synthesizers/regular/dragan/model.py
ydata_synthetic/synthesizers/regular/gmm/__init__.py
ydata_synthetic/synthesizers/regular/gmm/model.py
ydata_synthetic/synthesizers/regular/vanillagan/__init__.py
ydata_synthetic/synthesizers/regular/vanillagan/model.py
ydata_synthetic/synthesizers/regular/wgan/__init__.py
ydata_synthetic/synthesizers/regular/wgan/model.py
ydata_synthetic/synthesizers/regular/wgangp/__init__.py
ydata_synthetic/synthesizers/regular/wgangp/model.py
ydata_synthetic/synthesizers/timeseries/__init__.py
ydata_synthetic/synthesizers/timeseries/doppelganger/__init__.py
ydata_synthetic/synthesizers/timeseries/doppelganger/model.py
ydata_synthetic/synthesizers/timeseries/timegan/__init__.py
ydata_synthetic/synthesizers/timeseries/timegan/model.py
ydata_synthetic-2.0.0.dist-info/LICENSE
ydata_synthetic-2.0.0.dist-info/METADATA
ydata_synthetic-2.0.0.dist-info/WHEEL
ydata_synthetic-2.0.0.dist-info/top_level.txt
ydata_synthetic-2.0.0.dist-info/RECORD
